git_wiki_builder/__init__.py
git_wiki_builder/ai_client.py
git_wiki_builder/cli.py
git_wiki_builder/config.py
git_wiki_builder/content_analyzer.py
git_wiki_builder/generator.py
git_wiki_builder/prompt_manager.py
git_wiki_builder/publisher.py
git_wiki_builder/utils.py
git_wiki_builder/validator.py
git_wiki_builder/templates/config-template.yml
git_wiki_builder/templates/default-config.yml
git_wiki_builder/templates/default-prompts.yml
git_wiki_builder-0.1.4.dist-info/licenses/LICENSE
git_wiki_builder-0.1.4.dist-info/METADATA
git_wiki_builder-0.1.4.dist-info/WHEEL
git_wiki_builder-0.1.4.dist-info/entry_points.txt
git_wiki_builder-0.1.4.dist-info/top_level.txt
git_wiki_builder-0.1.4.dist-info/RECORD
